pysuma/__init__.py
pysuma/abstractive.py
pysuma/cli.py
pysuma/extractive.py
pysummarizer/__init__.py
pysummarizer/abstractive.py
pysummarizer/cli.py
pysummarizer/extractive.py
pysuma-0.1.0.dist-info/LICENSE
pysuma-0.1.0.dist-info/METADATA
pysuma-0.1.0.dist-info/WHEEL
pysuma-0.1.0.dist-info/top_level.txt
pysuma-0.1.0.dist-info/RECORD
